data/practical 2.ipynb
data/practical 3.ipynb
data/practical 6.ipynb
data/practical_4.ipynb
data/practical_5.ipynb
file/__init__.py
file/file2.py
mcbcdc-0.14.dist-info/METADATA
mcbcdc-0.14.dist-info/WHEEL
mcbcdc-0.14.dist-info/top_level.txt
mcbcdc-0.14.dist-info/RECORD
