Metadata-Version: 2.1
Name: mcbcdc
Version: 0.14
Summary: Description of your library
Author: JAY SHREE RAM
Author-email: kkwieer@yahoo.com
